{
	"galaxyId": "galaxy1",
	"systemId": "system208",
	"position": [
		209,
		66
	],
	"space": {
		"blurs": 196,
		"stars": 6489,
		"ambient_level": 0.1
	},
	"bodies": [
		{
			"type": "planet",
			"class": "habitable",
			"id": "Laeser",
			"name": "Laeser",
			"seed": "20 66 80 209 166 213",
			"body": {
				"radius": 4305,
				"rotation_v": 0.002707,
				"terminator_threshold_vector": [
					0.105,
					0.18,
					0.28
				]
			},
			"orbit": {
				"type": "static",
				"parent": "primary",
				"radius": 430500
			},
			"land": {
				"color": [
					0.539062,
					0.459045,
					0.494678,
					1
				],
				"polar_color": [
					0.946094,
					0.910985,
					0.926619,
					1
				]
			},
			"sea": {
				"color": [
					0.678624,
					0.769531,
					0.532059,
					1
				],
				"polar": [
					0.895786,
					0.923047,
					0.851835,
					1
				]
			},
			"atmosphere": {
				"color": [
					0.459204,
					0.482035,
					0.926156,
					1
				],
				"color_ratio": 0.5,
				"density": 0.75
			},
			"cloud": {
				"alpha": 1,
				"color": [
					0.0671387,
					0.161982,
					0.78125,
					1
				],
				"fraction": 0.32,
				"polar_color": [
					0.365074,
					0.429686,
					0.851562,
					1
				]
			},
			"demographics": {
				"type": 33,
				"productivity": 12672,
				"techLevel": 7,
				"economy": 2,
				"government": 2,
				"description": "This planet is beset by dreadful earthquakes.",
				"inhabitants": "Bony Birds"
			}
		},
		{
			"type": "star",
			"id": "primary",
			"name": "primary",
			"color": [
				0.671384,
				0.645498,
				0.565315,
				1
			],
			"radius": 97981.842041,
			"orbit": {
				"type": "static",
				"parent": null,
				"radius": 430500,
				"vector": [
					-0.1,
					-0.995,
					0.005
				]
			},
			"corona": {
				"shimmer": 0.40393,
				"hues": 0.672096,
				"flare": 0.020418
			}
		}
	],
	"stations": [
		{
			"type": "coriolis",
			"orbit": {
				"type": "static",
				"parent": "Laeser",
				"radius": 8610
			}
		}
	]
}