{
	"galaxyId": "galaxy4",
	"systemId": "system46",
	"position": [
		96,
		255
	],
	"space": {
		"blurs": 79,
		"stars": 6485,
		"ambient_level": 0.1
	},
	"bodies": [
		{
			"type": "planet",
			"class": "habitable",
			"id": "Isrite",
			"name": "Isrite",
			"seed": "188 255 136 96 245 93",
			"body": {
				"radius": 6240,
				"rotation_v": 0.00408,
				"terminator_threshold_vector": [
					0.105,
					0.18,
					0.28
				]
			},
			"orbit": {
				"type": "static",
				"parent": "primary",
				"radius": 873600
			},
			"land": {
				"color": [
					0.609375,
					0.399902,
					0.557007,
					1
				],
				"polar_color": [
					0.939062,
					0.858362,
					0.918887,
					1
				]
			},
			"sea": {
				"color": [
					0.810547,
					0.730798,
					0.417938,
					1
				],
				"polar": [
					0.918945,
					0.896342,
					0.807667,
					1
				]
			},
			"atmosphere": {
				"color": [
					0.601803,
					0.510285,
					0.918352,
					1
				],
				"color_ratio": 0.5,
				"density": 0.75
			},
			"cloud": {
				"alpha": 1,
				"color": [
					0.5839,
					0.201294,
					0.757812,
					1
				],
				"fraction": 0.58,
				"polar_color": [
					0.720387,
					0.455003,
					0.841016,
					1
				]
			},
			"demographics": {
				"type": 13,
				"productivity": 1560,
				"techLevel": 1,
				"economy": 7,
				"government": 1,
				"description": "This planet is noted for its exciting sit coms.",
				"inhabitants": "Yellow Rodents"
			}
		},
		{
			"type": "star",
			"id": "primary",
			"name": "primary",
			"color": [
				0.826895,
				0.790198,
				0.763284,
				1
			],
			"radius": 165557.666016,
			"orbit": {
				"type": "static",
				"parent": null,
				"radius": 374400,
				"vector": [
					-0.581,
					-0.349,
					-0.735
				]
			},
			"corona": {
				"shimmer": 0.369442,
				"hues": 0.590775,
				"flare": 0.014023
			}
		}
	],
	"stations": [
		{
			"type": "coriolis",
			"orbit": {
				"type": "static",
				"parent": "Isrite",
				"radius": 12480
			}
		}
	]
}