{
	"galaxyId": "galaxy3",
	"systemId": "system228",
	"position": [
		69,
		122
	],
	"space": {
		"blurs": 151,
		"stars": 7932,
		"ambient_level": 0.1
	},
	"bodies": [
		{
			"type": "planet",
			"class": "habitable",
			"id": "Velaat",
			"name": "Velaat",
			"seed": "50 122 98 69 26 150",
			"body": {
				"radius": 4421,
				"rotation_v": 0.001953,
				"terminator_threshold_vector": [
					0.105,
					0.18,
					0.28
				]
			},
			"orbit": {
				"type": "static",
				"parent": "primary",
				"radius": 442100
			},
			"land": {
				"color": [
					0.629183,
					0.66,
					0.543984,
					1
				],
				"polar_color": [
					0.923097,
					0.934,
					0.892955,
					1
				]
			},
			"sea": {
				"color": [
					0.0141525,
					0.724609,
					0.574747,
					1
				],
				"polar": [
					0.700183,
					0.927539,
					0.879581,
					1
				]
			},
			"atmosphere": {
				"color": [
					0.557557,
					0.50841,
					0.908596,
					1
				],
				"color_ratio": 0.5,
				"density": 0.75
			},
			"cloud": {
				"alpha": 1,
				"color": [
					0.403587,
					0.202049,
					0.728516,
					1
				],
				"fraction": 0.2,
				"polar_color": [
					0.597066,
					0.453933,
					0.827832,
					1
				]
			},
			"demographics": {
				"type": 39,
				"productivity": 19968,
				"techLevel": 8,
				"economy": 2,
				"government": 4,
				"description": "This world is fabled for its weird volcanoes.",
				"inhabitants": "Human Colonials"
			}
		},
		{
			"type": "star",
			"id": "primary",
			"name": "primary",
			"color": [
				0.209035,
				0.478246,
				0.689343,
				1
			],
			"radius": 122823.469696,
			"orbit": {
				"type": "static",
				"parent": null,
				"radius": 353680,
				"vector": [
					0.955,
					0.244,
					0.17
				]
			},
			"corona": {
				"shimmer": 0.329887,
				"hues": 0.784927,
				"flare": 0.065511
			}
		}
	],
	"stations": [
		{
			"type": "coriolis",
			"orbit": {
				"type": "static",
				"parent": "Velaat",
				"radius": 8842
			}
		}
	]
}