{
	"galaxyId": "galaxy3",
	"systemId": "system145",
	"position": [
		202,
		182
	],
	"space": {
		"blurs": 180,
		"stars": 5628,
		"ambient_level": 0.1
	},
	"bodies": [
		{
			"type": "planet",
			"class": "habitable",
			"id": "Cecela",
			"name": "Cecela",
			"seed": "138 182 82 202 10 5",
			"body": {
				"radius": 4298,
				"rotation_v": 0.004407,
				"terminator_threshold_vector": [
					0.105,
					0.18,
					0.28
				]
			},
			"orbit": {
				"type": "static",
				"parent": "primary",
				"radius": 386820
			},
			"land": {
				"color": [
					0.66,
					0.193359,
					0.598024,
					1
				],
				"polar_color": [
					0.934,
					0.768908,
					0.912074,
					1
				]
			},
			"sea": {
				"color": [
					0.671875,
					0.648695,
					0.497345,
					1
				],
				"polar": [
					0.932813,
					0.924767,
					0.872234,
					1
				]
			},
			"atmosphere": {
				"color": [
					0.787814,
					0.626238,
					0.873475,
					1
				],
				"color_ratio": 0.5,
				"density": 0.75
			},
			"cloud": {
				"alpha": 1,
				"color": [
					0.623047,
					0.467285,
					0.470936,
					1
				],
				"fraction": 0.19,
				"polar_color": [
					0.780371,
					0.658438,
					0.661296,
					1
				]
			},
			"demographics": {
				"type": 25,
				"productivity": 4800,
				"techLevel": 4,
				"economy": 6,
				"government": 2,
				"description": "This world is most fabled for its inhabitants’ eccentric love for tourists but beset by lethal disease.",
				"inhabitants": "Human Colonials"
			}
		},
		{
			"type": "star",
			"id": "primary",
			"name": "primary",
			"color": [
				0.556791,
				0.59716,
				0.727139,
				1
			],
			"radius": 101590.223694,
			"orbit": {
				"type": "static",
				"parent": null,
				"radius": 429800,
				"vector": [
					-0.766,
					-0.634,
					-0.102
				]
			},
			"corona": {
				"shimmer": 0.439132,
				"hues": 0.535973,
				"flare": 0.064827
			}
		}
	],
	"stations": [
		{
			"type": "coriolis",
			"orbit": {
				"type": "static",
				"parent": "Cecela",
				"radius": 8596
			}
		}
	]
}