{
	"galaxyId": "galaxy0",
	"systemId": "system19",
	"position": [
		6,
		110
	],
	"space": {
		"blurs": 84,
		"stars": 9008,
		"ambient_level": 0.1
	},
	"bodies": [
		{
			"type": "planet",
			"class": "habitable",
			"id": "Azaqu",
			"name": "Azaqu",
			"seed": "152 110 52 6 205 47",
			"body": {
				"radius": 6662,
				"rotation_v": 0.001077,
				"terminator_threshold_vector": [
					0.105,
					0.18,
					0.28
				]
			},
			"orbit": {
				"type": "static",
				"parent": "primary",
				"radius": 799440
			},
			"land": {
				"color": [
					0.198833,
					0.599609,
					0.0538712,
					1
				],
				"polar_color": [
					0.782959,
					0.940039,
					0.726143,
					1
				]
			},
			"sea": {
				"color": [
					1,
					0.75,
					0.81,
					1
				],
				"polar": [
					0.9,
					0.84375,
					0.85725,
					1
				]
			},
			"atmosphere": {
				"color": [
					0.556143,
					0.546926,
					0.863068,
					1
				],
				"color_ratio": 0.5,
				"density": 0.75
			},
			"cloud": {
				"alpha": 1,
				"color": [
					0.325951,
					0.295898,
					0.591797,
					1
				],
				"fraction": 0.42,
				"polar_color": [
					0.551158,
					0.526837,
					0.766309,
					1
				]
			},
			"demographics": {
				"type": 37,
				"productivity": 11840,
				"techLevel": 6,
				"economy": 6,
				"government": 6,
				"description": "The planet Azaqu is most famous for its pink oceans and Zero-G cricket.",
				"inhabitants": "Red Slimy Lobsters"
			}
		},
		{
			"type": "star",
			"id": "primary",
			"name": "primary",
			"color": [
				0.584958,
				0.809818,
				0.833252,
				1
			],
			"radius": 179628.810425,
			"orbit": {
				"type": "static",
				"parent": null,
				"radius": 599580,
				"vector": [
					0.206,
					-0.474,
					-0.856
				]
			},
			"corona": {
				"shimmer": 0.350843,
				"hues": 0.602066,
				"flare": 0.038925
			}
		}
	],
	"stations": [
		{
			"type": "coriolis",
			"orbit": {
				"type": "static",
				"parent": "Azaqu",
				"radius": 13324
			}
		}
	]
}