{
	"galaxyId": "galaxy0",
	"systemId": "system58",
	"position": [
		70,
		117
	],
	"space": {
		"blurs": 81,
		"stars": 7602,
		"ambient_level": 0.1
	},
	"bodies": [
		{
			"type": "planet",
			"class": "habitable",
			"id": "Uscela",
			"name": "Uscela",
			"seed": "138 117 236 70 219 72",
			"body": {
				"radius": 4934,
				"rotation_v": 0.004926,
				"terminator_threshold_vector": [
					0.105,
					0.18,
					0.28
				]
			},
			"orbit": {
				"type": "static",
				"parent": "primary",
				"radius": 444060
			},
			"land": {
				"color": [
					0.405894,
					0.66,
					0.232031,
					1
				],
				"polar_color": [
					0.8441,
					0.934,
					0.78259,
					1
				]
			},
			"sea": {
				"color": [
					0.597656,
					0.473146,
					0.448709,
					1
				],
				"polar": [
					0.940234,
					0.891264,
					0.881653,
					1
				]
			},
			"atmosphere": {
				"color": [
					0.671664,
					0.601788,
					0.845508,
					1
				],
				"color_ratio": 0.5,
				"density": 0.75
			},
			"cloud": {
				"alpha": 1,
				"color": [
					0.521164,
					0.395874,
					0.539062,
					1
				],
				"fraction": 0.48,
				"polar_color": [
					0.727168,
					0.619299,
					0.742578,
					1
				]
			},
			"demographics": {
				"type": 39,
				"productivity": 14040,
				"techLevel": 7,
				"economy": 5,
				"government": 5,
				"description": "The world Uscela is a boring world.",
				"inhabitants": "Small Yellow Bony Lobsters"
			}
		},
		{
			"type": "star",
			"id": "primary",
			"name": "primary",
			"color": [
				0.331434,
				0.507403,
				0.70946,
				1
			],
			"radius": 125575.479736,
			"orbit": {
				"type": "static",
				"parent": null,
				"radius": 444060,
				"vector": [
					-0.203,
					0.11,
					-0.973
				]
			},
			"corona": {
				"shimmer": 0.364676,
				"hues": 0.702057,
				"flare": 0.089973
			}
		}
	],
	"stations": [
		{
			"type": "coriolis",
			"orbit": {
				"type": "static",
				"parent": "Uscela",
				"radius": 9868
			}
		}
	]
}