{
	"galaxyId": "galaxy5",
	"systemId": "system152",
	"position": [
		7,
		9
	],
	"space": {
		"blurs": 45,
		"stars": 7675,
		"ambient_level": 0.1
	},
	"bodies": [
		{
			"type": "planet",
			"class": "habitable",
			"id": "Dirien",
			"name": "Dirien",
			"seed": "169 9 25 7 74 173",
			"body": {
				"radius": 6151,
				"rotation_v": 0.004728,
				"terminator_threshold_vector": [
					0.105,
					0.18,
					0.28
				]
			},
			"orbit": {
				"type": "static",
				"parent": "primary",
				"radius": 922650
			},
			"land": {
				"color": [
					0.595703,
					0.409546,
					0.549164,
					1
				],
				"polar_color": [
					0.94043,
					0.866959,
					0.922062,
					1
				]
			},
			"sea": {
				"color": [
					0.644531,
					0.61221,
					0.485413,
					1
				],
				"polar": [
					0.935547,
					0.923818,
					0.877806,
					1
				]
			},
			"atmosphere": {
				"color": [
					0.671881,
					0.863348,
					0.902742,
					1
				],
				"color_ratio": 0.5,
				"density": 0.75
			},
			"cloud": {
				"alpha": 1,
				"color": [
					0.648431,
					0.710938,
					0.591522,
					1
				],
				"fraction": 0.49,
				"polar_color": [
					0.774867,
					0.819922,
					0.733846,
					1
				]
			},
			"demographics": {
				"type": 49,
				"productivity": 24696,
				"techLevel": 11,
				"economy": 1,
				"government": 3,
				"description": "This planet is most fabled for Dirienian Bein brandy but cursed by unpredictable solar activity.",
				"inhabitants": "Human Colonials"
			}
		},
		{
			"type": "star",
			"id": "primary",
			"name": "primary",
			"color": [
				0.334426,
				0.433262,
				0.774677,
				1
			],
			"radius": 153194.964905,
			"orbit": {
				"type": "static",
				"parent": null,
				"radius": 492080,
				"vector": [
					-0.052,
					-0.945,
					0.324
				]
			},
			"corona": {
				"shimmer": 0.38192,
				"hues": 0.99437,
				"flare": 0.027112
			}
		}
	],
	"stations": [
		{
			"type": "dodecahedron",
			"orbit": {
				"type": "static",
				"parent": "Dirien",
				"radius": 12302
			}
		}
	]
}