{
	"galaxyId": "galaxy7",
	"systemId": "system26",
	"position": [
		14,
		17
	],
	"space": {
		"blurs": 120,
		"stars": 8166,
		"ambient_level": 0.1
	},
	"bodies": [
		{
			"type": "planet",
			"class": "habitable",
			"id": "Titiridi",
			"name": "Titiridi",
			"seed": "121 17 168 14 181 55",
			"body": {
				"radius": 4622,
				"rotation_v": 0.002801,
				"terminator_threshold_vector": [
					0.105,
					0.18,
					0.28
				]
			},
			"orbit": {
				"type": "static",
				"parent": "primary",
				"radius": 600860
			},
			"land": {
				"color": [
					0.634622,
					0.543984,
					0.66,
					1
				],
				"polar_color": [
					0.925021,
					0.892955,
					0.934,
					1
				]
			},
			"sea": {
				"color": [
					0.642578,
					0.629398,
					0.489213,
					1
				],
				"polar": [
					0.935742,
					0.930944,
					0.879908,
					1
				]
			},
			"atmosphere": {
				"color": [
					0.439182,
					0.563246,
					0.917051,
					1
				],
				"color_ratio": 0.5,
				"density": 0.75
			},
			"cloud": {
				"alpha": 1,
				"color": [
					0.0265045,
					0.583421,
					0.753906,
					1
				],
				"fraction": 0.35,
				"polar_color": [
					0.333162,
					0.720642,
					0.839258,
					1
				]
			},
			"demographics": {
				"type": 51,
				"productivity": 33048,
				"techLevel": 11,
				"economy": 1,
				"government": 5,
				"description": "The planet Titiridi is reasonably noted for its inhabitants’ eccentric shyness and its inhabitants’ eccentric love for poetry.",
				"inhabitants": "Red Lizards"
			}
		},
		{
			"type": "star",
			"id": "primary",
			"name": "primary",
			"color": [
				0.839044,
				0.71882,
				0.683375,
				1
			],
			"radius": 120515.039062,
			"orbit": {
				"type": "static",
				"parent": null,
				"radius": 415980,
				"vector": [
					0.562,
					-0.521,
					0.642
				]
			},
			"corona": {
				"shimmer": 0.477007,
				"hues": 0.537186,
				"flare": 0.069566
			}
		}
	],
	"stations": [
		{
			"type": "dodecahedron",
			"orbit": {
				"type": "static",
				"parent": "Titiridi",
				"radius": 9244
			}
		}
	]
}